lexipy/__init__.py
lexipy/lexer.py
lexipy-0.1.0.dist-info/METADATA
lexipy-0.1.0.dist-info/WHEEL
lexipy-0.1.0.dist-info/RECORD
